flask_querymonitor/__init__.py
flask_querymonitor/monitor.py
flask_querymonitor-1.0.3.dist-info/licenses/LICENSE
flask_querymonitor-1.0.3.dist-info/METADATA
flask_querymonitor-1.0.3.dist-info/WHEEL
flask_querymonitor-1.0.3.dist-info/top_level.txt
flask_querymonitor-1.0.3.dist-info/RECORD
