Metadata-Version: 2.4
Name: flask-querymonitor
Version: 1.0.3
Summary: Detect and eliminate N+1 queries in Flask-SQLAlchemy
Home-page: https://github.com/wallmarkets/flask-querymonitor
Author: wallmarkets Team
Author-email: team@wallmarkets.store
Project-URL: Bug Reports, https://github.com/wallmarkets/flask-querymonitor/issues
Project-URL: Source, https://github.com/wallmarkets/flask-querymonitor
Keywords: flask sqlalchemy n+1 query-monitoring performance optimization
Classifier: Development Status :: 5 - Production/Stable
Classifier: Intended Audience :: Developers
Classifier: License :: OSI Approved :: MIT License
Classifier: Programming Language :: Python :: 3
Classifier: Programming Language :: Python :: 3.7
Classifier: Programming Language :: Python :: 3.8
Classifier: Programming Language :: Python :: 3.9
Classifier: Programming Language :: Python :: 3.10
Classifier: Programming Language :: Python :: 3.11
Classifier: Framework :: Flask
Requires-Python: >=3.7
License-File: LICENSE
Requires-Dist: Flask>=2.0.0
Requires-Dist: Flask-SQLAlchemy>=3.0.0
Dynamic: author
Dynamic: author-email
Dynamic: classifier
Dynamic: description
Dynamic: description-content-type
Dynamic: home-page
Dynamic: keywords
Dynamic: license-file
Dynamic: project-url
Dynamic: requires-dist
Dynamic: requires-python
Dynamic: summary
